fast_yaml/__init__.py
fast_yaml/_core.cpython-310-darwin.so
fast_yaml/_core.pyi
fast_yaml/lint.py
fast_yaml/parallel.py
fast_yaml/py.typed
fastyaml_rs-0.5.0.dist-info/METADATA
fastyaml_rs-0.5.0.dist-info/WHEEL
fastyaml_rs-0.5.0.dist-info/RECORD
