Metadata-Version: 2.4
Name: fastyaml-rs
Version: 0.5.0
Classifier: Development Status :: 4 - Beta
Classifier: Intended Audience :: Developers
Classifier: License :: OSI Approved :: MIT License
Classifier: License :: OSI Approved :: Apache Software License
Classifier: Programming Language :: Python :: 3
Classifier: Programming Language :: Python :: 3.10
Classifier: Programming Language :: Python :: 3.11
Classifier: Programming Language :: Python :: 3.12
Classifier: Programming Language :: Python :: 3.13
Classifier: Programming Language :: Python :: 3.14
Classifier: Programming Language :: Rust
Classifier: Topic :: Software Development :: Libraries :: Python Modules
Classifier: Topic :: Text Processing :: Markup
Classifier: Typing :: Typed
Summary: A fast YAML parser and linter for Python, powered by Rust
Keywords: yaml,parser,linter,rust,performance
Author: fast-yaml contributors
License: MIT OR Apache-2.0
Requires-Python: >=3.10
Project-URL: Documentation, https://github.com/bug-ops/fast-yaml#readme
Project-URL: Homepage, https://github.com/bug-ops/fast-yaml
Project-URL: Repository, https://github.com/bug-ops/fast-yaml
